prompt_learner/.DS_Store
prompt_learner/adapters/__init__.py
prompt_learner/adapters/adapter.py
prompt_learner/adapters/anthropic.py
prompt_learner/adapters/llama.py
prompt_learner/adapters/ollama_local.py
prompt_learner/adapters/openai.py
prompt_learner/evals/metrics/accuracy.py
prompt_learner/examples/__init__.py
prompt_learner/examples/example.py
prompt_learner/examples/manipulation/__init__.py
prompt_learner/inference/__init__.py
prompt_learner/inference/predict.py
prompt_learner/optimizers/__init__.py
prompt_learner/optimizers/grid_search.py
prompt_learner/optimizers/optimizer.py
prompt_learner/prompts/__init__.py
prompt_learner/prompts/cot.py
prompt_learner/prompts/prompt.py
prompt_learner/selectors/__init__.py
prompt_learner/selectors/diverse_sampler.py
prompt_learner/selectors/random_sampler.py
prompt_learner/selectors/selector.py
prompt_learner/selectors/stratified_sampler.py
prompt_learner/tasks/__init__.py
prompt_learner/tasks/classification.py
prompt_learner/tasks/sql_generation.py
prompt_learner/tasks/tagging.py
prompt_learner/tasks/task.py
prompt_learner/templates/__init__.py
prompt_learner/templates/markdown.py
prompt_learner/templates/template.py
prompt_learner/templates/xml.py
prompt_learner/translator/translate.py
prompt_learner-0.3.3.dist-info/METADATA
prompt_learner-0.3.3.dist-info/WHEEL
prompt_learner-0.3.3.dist-info/RECORD
