Metadata-Version: 2.1
Name: prompt-learner
Version: 0.3.3
Summary: 
Author: Aditya Lahiri
Author-email: adityalahiri13@gmail.com
Requires-Python: >=3.11,<4.0
Classifier: Programming Language :: Python :: 3
Classifier: Programming Language :: Python :: 3.11
Classifier: Programming Language :: Python :: 3.12
Requires-Dist: black (>=24.3.0,<25.0.0)
Requires-Dist: langchain (>=0.1.13,<0.2.0)
Requires-Dist: langchain-anthropic (>=0.1.4,<0.2.0)
Requires-Dist: langchain-fireworks (>=0.1.2,<0.2.0)
Requires-Dist: langchain-groq (>=0.1.3,<0.2.0)
Requires-Dist: langchain-openai (>=0.1.5,<0.2.0)
Requires-Dist: python-dotenv (>=1.0.1,<2.0.0)
Requires-Dist: scikit-learn (>=1.4.2,<2.0.0)
